.gitignore
6acf770552fca63f1538__mypyc.cp311-win_amd64.pyd
asgi_etags-0.2.1.dist-info/METADATA
asgi_etags-0.2.1.dist-info/WHEEL
asgi_etags-0.2.1.dist-info/licenses/LICENSE
asgi_etags/__init__.cp311-win_amd64.pyd
asgi_etags/__init__.py
asgi_etags/core.cp311-win_amd64.pyd
asgi_etags/core.py
asgi_etags/py.typed
asgi_etags/types.cp311-win_amd64.pyd
asgi_etags/types.py
asgi_etags-0.2.1.dist-info/RECORD
