Metadata-Version: 2.1
Name: asgi_etags
Version: 0.2.1
Author-Email: Marcin Paliwoda <boringstuffinc@gmail.com>
License: MIT
Requires-Python: >=3.11
Requires-Dist: mypy-extensions>=1.0.0
